ctec_consumer/__init__.py
ctec_consumer/__version__.py
ctec_consumer/consumer_log.py
ctec_consumer/ctec_consumer.py
ctec_consumer/dummy/__init__.py
ctec_consumer/dummy/ctec_consumer.py
ctec_consumer/dummy/models/__init__.py
ctec_consumer/dummy/models/worker_message.py
ctec_consumer/gevent/__init__.py
ctec_consumer/gevent/ctec_consumer.py
ctec_consumer/gevent/models/__init__.py
ctec_consumer/gevent/models/worker_message.py
ctec_consumer/models/__init__.py
ctec_consumer/models/worker_message.py
ctec_consumer2-0.0.2.dist-info/METADATA
ctec_consumer2-0.0.2.dist-info/WHEEL
ctec_consumer2-0.0.2.dist-info/top_level.txt
ctec_consumer2-0.0.2.dist-info/RECORD
